powerlogger/__init__.py
powerlogger/powerlogger.py
powerlogger-1.0.6.dist-info/licenses/LICENSE
powerlogger-1.0.6.dist-info/METADATA
powerlogger-1.0.6.dist-info/WHEEL
powerlogger-1.0.6.dist-info/top_level.txt
powerlogger-1.0.6.dist-info/RECORD
