Metadata-Version: 2.4
Name: powerlogger
Version: 1.0.6
Summary: Enhanced logging functionality with Rich console output and file rotation
Home-page: https://github.com/Pandiyarajk/powerlogger
Author: Pandiyaraj Karuppasamy
Author-email: Pandiyaraj Karuppasamy <pandiyarajk@live.com>
Maintainer-email: Pandiyaraj Karuppasamy <pandiyarajk@live.com>
License: MIT
Project-URL: Homepage, https://github.com/Pandiyarajk/powerlogger
Project-URL: Bug Tracker, https://github.com/Pandiyarajk/powerlogger/issues
Project-URL: Changelog, https://github.com/Pandiyarajk/powerlogger/blob/main/CHANGELOG.md
Project-URL: Documentation, https://github.com/Pandiyarajk/powerlogger/blob/main/README.md
Project-URL: Repository, https://github.com/Pandiyarajk/powerlogger
Keywords: logging,rich,console,unicode,file-rotation,thread-safe,windows
Classifier: Development Status :: 5 - Production/Stable
Classifier: Intended Audience :: Developers
Classifier: License :: OSI Approved :: MIT License
Classifier: Operating System :: OS Independent
Classifier: Programming Language :: Python :: 3
Classifier: Programming Language :: Python :: 3.11
Classifier: Programming Language :: Python :: 3.12
Classifier: Programming Language :: Python :: 3.13
Classifier: Topic :: Software Development :: Libraries :: Python Modules
Classifier: Topic :: System :: Logging
Requires-Python: >=3.11
License-File: LICENSE
Requires-Dist: rich>=13.0.0
Provides-Extra: dev
Requires-Dist: pytest>=7.0.0; extra == "dev"
Requires-Dist: pytest-cov>=4.0.0; extra == "dev"
Requires-Dist: black>=23.0.0; extra == "dev"
Requires-Dist: flake8>=6.0.0; extra == "dev"
Requires-Dist: isort>=5.12.0; extra == "dev"
Requires-Dist: mypy>=1.0.0; extra == "dev"
Requires-Dist: safety>=2.0.0; extra == "dev"
Requires-Dist: bandit>=1.7.0; extra == "dev"
Requires-Dist: pytest-benchmark>=4.0.0; extra == "dev"
Dynamic: author
Dynamic: home-page
Dynamic: license-file
Dynamic: requires-python
